README.rst
setup.py
tbotg/__init__.py
tbotg.egg-info/PKG-INFO
tbotg.egg-info/SOURCES.txt
tbotg.egg-info/dependency_links.txt
tbotg.egg-info/entry_points.txt
tbotg.egg-info/requires.txt
tbotg.egg-info/top_level.txt
tbotg/core/__init__.py
tbotg/core/bcmds.py
tbotg/core/callback_tools.py
tbotg/core/examples.py
tbotg/core/main_bot.py
tbotg/scripts/__init__.py
tbotg/scripts/tcli.py