Metadata-Version: 1.1
Name: tbotg
Version: 0.3.0
Summary: Tools for Telegram generic bots.
Home-page: http://github.com/aocks/tbotg
Author: Emin Martinian
Author-email: emin.martinian@gmail.com
License: GPL3
Keywords: telegram generic bots
Platform: UNKNOWN
Classifier: Development Status :: 3 - Alpha
Classifier: Intended Audience :: Developers
Classifier: Programming Language :: Python :: 3
